common/__init__.py
common/singleton.py
common/terminal_font.py
mqtt_helper/__init__.py
mqtt_helper/mqtt_helper.py
Vonpylib_voicevon-0.0.4.dist-info/LICENSE
Vonpylib_voicevon-0.0.4.dist-info/METADATA
Vonpylib_voicevon-0.0.4.dist-info/WHEEL
Vonpylib_voicevon-0.0.4.dist-info/top_level.txt
Vonpylib_voicevon-0.0.4.dist-info/RECORD
