Metadata-Version: 2.1
Name: Vonpylib-voicevon
Version: 0.0.4
Summary: Greet to joint me, or I want to joint you.
Home-page: https://github.com/voicevon/VonPylib
Author: Xuming Feng
Author-email: voicevon@gmail.com
License: UNKNOWN
Project-URL: Bug Tracker, https://github.com/voicevon/VonPylib
Platform: UNKNOWN
Classifier: Programming Language :: Python :: 3
Classifier: License :: OSI Approved :: MIT License
Classifier: Operating System :: OS Independent
Requires-Python: >=3.6
License-File: LICENSE
